catch/__init__.py
catch/catch.py
catch/cli.py
catch-0.1.0.dist-info/DESCRIPTION.rst
catch-0.1.0.dist-info/METADATA
catch-0.1.0.dist-info/RECORD
catch-0.1.0.dist-info/WHEEL
catch-0.1.0.dist-info/entry_points.txt
catch-0.1.0.dist-info/metadata.json
catch-0.1.0.dist-info/pbr.json
catch-0.1.0.dist-info/top_level.txt
