Metadata-Version: 2.0
Name: catch
Version: 0.1.0
Summary: Web crawler with built in parsers usng latest Python technologies
Home-page: https://github.com/umrashrf/catch
Author: Umair Ashraf
Author-email: umrashrf@gmail.com
License: GNU General Public License v3
Keywords: catch
Platform: UNKNOWN
Classifier: Development Status :: 2 - Pre-Alpha
Classifier: Intended Audience :: Developers
Classifier: License :: OSI Approved :: GNU General Public License v3 (GPLv3)
Classifier: Natural Language :: English
Classifier: Programming Language :: Python :: 2
Classifier: Programming Language :: Python :: 2.7
Classifier: Programming Language :: Python :: 3
Classifier: Programming Language :: Python :: 3.4
Classifier: Programming Language :: Python :: 3.5
Classifier: Programming Language :: Python :: 3.6
Requires-Dist: Click (>=6.0)
